scrapy_playwright_patched/__init__.py
scrapy_playwright_patched/_utils.py
scrapy_playwright_patched/handler.py
scrapy_playwright_patched/headers.py
scrapy_playwright_patched/memusage.py
scrapy_playwright_patched/page.py
scrapy_playwright_patched-0.42.dist-info/METADATA
scrapy_playwright_patched-0.42.dist-info/WHEEL
scrapy_playwright_patched-0.42.dist-info/RECORD
